XiaofeipinShengtaiQuanLianluShuzhihuaZhuanxingBaipishuFix1/README.md
XiaofeipinShengtaiQuanLianluShuzhihuaZhuanxingBaipishuFix1/__init__.py
XiaofeipinShengtaiQuanLianluShuzhihuaZhuanxingBaipishuFix1/__main__.py
XiaofeipinShengtaiQuanLianluShuzhihuaZhuanxingBaipishuFix1/file.pdf
XiaofeipinShengtaiQuanLianluShuzhihuaZhuanxingBaipishuFix1/index.html
xiaofeipin_shengtai_quan_lianlu_shuzhihua_zhuanxing_baipishu_fix1-2025.3.25.0.dist-info/METADATA
xiaofeipin_shengtai_quan_lianlu_shuzhihua_zhuanxing_baipishu_fix1-2025.3.25.0.dist-info/WHEEL
xiaofeipin_shengtai_quan_lianlu_shuzhihua_zhuanxing_baipishu_fix1-2025.3.25.0.dist-info/entry_points.txt
xiaofeipin_shengtai_quan_lianlu_shuzhihua_zhuanxing_baipishu_fix1-2025.3.25.0.dist-info/top_level.txt
xiaofeipin_shengtai_quan_lianlu_shuzhihua_zhuanxing_baipishu_fix1-2025.3.25.0.dist-info/RECORD
